mrtinydbutils/__init__.py
mrtinydbutils/middlewares.py
mrtinydbutils/py.typed
mrtinydbutils/tables.py
mrtinydbutils/version.py
mrtinydbutils-0.1.1.dist-info/LICENSE
mrtinydbutils-0.1.1.dist-info/METADATA
mrtinydbutils-0.1.1.dist-info/WHEEL
mrtinydbutils-0.1.1.dist-info/top_level.txt
mrtinydbutils-0.1.1.dist-info/RECORD
