Metadata-Version: 2.1
Name: mrtinydbutils
Version: 0.1.1
Summary: mrtinydbutils - Utilities for the TinyDB
Home-page: https://anatas_ch.gitlab.io/pyl_mrtinydb/
Author: Michael Rippstein
Author-email: info@anatas.ch
License: AGPL-3.0
Project-URL: Documentation, https://mrtinydbutils.readthedocs.io/
Project-URL: Bug Tracker, https://gitlab.com/anatas_ch/pyl_mrtinydb/-/issues
Project-URL: Source Code, https://gitlab.com/anatas_ch/pyl_mrtinydb
Keywords: database,nosql
Platform: UNKNOWN
Classifier: Development Status :: 3 - Alpha
Classifier: Intended Audience :: Developers
Classifier: Intended Audience :: System Administrators
Classifier: License :: OSI Approved :: GNU Affero General Public License v3 or later (AGPLv3+)
Classifier: Topic :: Database
Classifier: Topic :: Database :: Database Engines/Servers
Classifier: Topic :: Utilities
Classifier: Programming Language :: Python :: 3
Classifier: Programming Language :: Python :: 3.9
Classifier: Programming Language :: Python :: Implementation :: CPython
Classifier: Programming Language :: Python :: Implementation :: PyPy
Classifier: Operating System :: OS Independent
Classifier: Typing :: Typed
Requires-Python: >=3.9
License-File: LICENSE
Requires-Dist: tinydb (>=4.4.0)
